torchlatent/__init__.py
torchlatent/abc.py
torchlatent/cky.py
torchlatent/crf.py
torchlatent/functional.py
torchlatent/semiring.py
torchlatent-0.4.3.dist-info/LICENSE
torchlatent-0.4.3.dist-info/METADATA
torchlatent-0.4.3.dist-info/WHEEL
torchlatent-0.4.3.dist-info/top_level.txt
torchlatent-0.4.3.dist-info/RECORD
